lakh_crore_numbers/__init__.py
lakh_crore_numbers/errors.py
lakh_crore_numbers/format.py
lakh_crore_numbers/parse.py
lakh_crore_numbers/languages/__init__.py
lakh_crore_numbers/languages/nepali.py
tests/__init__.py
tests/test_format.py
tests/test_init.py
tests/test_parse.py
lakh_crore_numbers-0.1.0.dist-info/LICENSE
lakh_crore_numbers-0.1.0.dist-info/METADATA
lakh_crore_numbers-0.1.0.dist-info/WHEEL
lakh_crore_numbers-0.1.0.dist-info/top_level.txt
lakh_crore_numbers-0.1.0.dist-info/RECORD
