Metadata-Version: 2.1
Name: lakh-crore-numbers
Version: 0.1.0
Summary: A Python library for formatting numbers into the Lakh Crore (...हजार, लाख, करोड, अर्ब...) system.
Home-page: https://github.com/suvash/lakh-crore-numbers/tree/main/python
Author: Suvash Thapaliya
Author-email: suvash@gmail.com
License: ISC License
Project-URL: Bug Tracker, https://github.com/suvash/lakh-crore-numbers/issues
Platform: UNKNOWN
Classifier: Topic :: Software Development :: Internationalization
Classifier: Topic :: Software Development :: Localization
Classifier: Development Status :: 1 - Planning
Classifier: License :: OSI Approved :: ISC License (ISCL)
Classifier: Programming Language :: Python :: 3.6
Classifier: Operating System :: OS Independent
Classifier: Intended Audience :: Developers
Classifier: Natural Language :: English
Classifier: Natural Language :: Nepali
Requires-Python: >=3.6
